slashcord/__init__.py
slashcord/_exceptions.py
slashcord/_http.py
slashcord/_settings.py
slashcord/tests.py
SlashCord-0.0.1.dist-info/LICENSE
SlashCord-0.0.1.dist-info/METADATA
SlashCord-0.0.1.dist-info/WHEEL
SlashCord-0.0.1.dist-info/top_level.txt
SlashCord-0.0.1.dist-info/RECORD
