Metadata-Version: 2.1
Name: SlashCord
Version: 0.0.1
Summary: Discord
Home-page: https://slashcord.readthedocs.io/en/latest/
Author: WardPearce
Author-email: wardpearce@protonmail.com
License: MIT
Platform: UNKNOWN
Requires-Python: >=3.6
Requires-Dist: aiohttp[speedups]
Requires-Dist: asynctest
Requires-Dist: sphinxcontrib-trio
Requires-Dist: sphinx-material
